pekl/Pekl.py
pekl/__init__.py
pekl-0.5.dist-info/DESCRIPTION.rst
pekl-0.5.dist-info/METADATA
pekl-0.5.dist-info/RECORD
pekl-0.5.dist-info/WHEEL
pekl-0.5.dist-info/metadata.json
pekl-0.5.dist-info/top_level.txt
