Metadata-Version: 2.0
Name: pekl
Version: 0.5
Summary: An AWS Lambda library for making invocations and responses with large bodies easier.
Home-page: https://github.com/tamme-io/pekl
Author: tamme
Author-email: opensource@tamme.io
License: MIT
Platform: UNKNOWN
Requires-Dist: boto3
Requires-Dist: netaddr
